gnssrefl0/__init__.py
gnssrefl0/download_rinex.py
gnssrefl0/gnssir.py
gnssrefl0/gnssir_cl.py
gnssrefl0/gnssir_guts.py
gnssrefl0/gnssrefl0.py
gnssrefl0/gps.py
gnssrefl0/gpt_1wA.pickle
gnssrefl0/make_json_input.py
gnssrefl0/plot_results.py
gnssrefl0/quickLook.py
gnssrefl0/quickLook_cl.py
gnssrefl0/quickLook_function.py
gnssrefl0/quick_read_snr.py
gnssrefl0/read_snr_files.py
gnssrefl0/refraction.py
gnssrefl0/rinex2snr.py
gnssrefl0/rinex2snr_cl.py
gnssrefl0/rinpy.py
gnssrefl0/rnx2snr.py
gnssrefl0/ymd.py
gnssrefl0-0.0.12.dist-info/LICENSE
gnssrefl0-0.0.12.dist-info/METADATA
gnssrefl0-0.0.12.dist-info/WHEEL
gnssrefl0-0.0.12.dist-info/entry_points.txt
gnssrefl0-0.0.12.dist-info/top_level.txt
gnssrefl0-0.0.12.dist-info/RECORD
