Metadata-Version: 2.1
Name: gnssrefl0
Version: 0.0.12
Summary: A GNSS reflectometry software package 
Home-page: https://github.com/kristinemlarson/gnssrefl0/
Author: Kristine Larson
Author-email: kristine.larson@colorado.edu
License: UNKNOWN
Platform: UNKNOWN
Classifier: Programming Language :: Python :: 3.7
Classifier: License :: OSI Approved :: GNU General Public License v3 (GPLv3)
Requires-Dist: numpy
Requires-Dist: wget
Requires-Dist: scipy
Requires-Dist: matplotlib
Requires-Dist: requests
